example/.github/workflows/deploy.yml
example/.gitignore
example/README.md
example/assets/css/pygments.css
example/assets/css/style.css
example/assets/images/demo.png
example/assets/js/.empty
example/build.py
example/content/index.md
example/content/posts/index.md
example/content/posts/lorem-ipsum.md
example/content/posts/markdown-syntax-guide.md
example/templates/_footer.liquid
example/templates/_head.liquid
example/templates/_header.liquid
example/templates/_pages.liquid
example/templates/default.liquid
example/templates/redirect.liquid
markupdown-0.2.5.dist-info/METADATA
markupdown-0.2.5.dist-info/WHEEL
markupdown-0.2.5.dist-info/entry_points.txt
markupdown-0.2.5.dist-info/licenses/LICENSE
markupdown/__init__.py
markupdown/__main__.py
markupdown/blurb.py
markupdown/changelog.py
markupdown/children.py
markupdown/clean.py
markupdown/cp.py
markupdown/feed.py
markupdown/files.py
markupdown/init.py
markupdown/link.py
markupdown/ls.py
markupdown/minify.py
markupdown/references.py
markupdown/render.py
markupdown/serve.py
markupdown/siblings.py
markupdown/sitemap.py
markupdown/title.py
markupdown/toc.py
markupdown/transform.py
markupdown/util.py
markupdown-0.2.5.dist-info/RECORD
