Metadata-Version: 2.1
Name: markupdown
Version: 0.2.5
Summary: A modular static site generator in Python
Author-Email: Chris Riccomini <criccomini@apache.org>
License: CC0-1.0
Requires-Python: <3.13,>=3.10
Requires-Dist: python-liquid>=1.12.2
Requires-Dist: python-frontmatter>=1.1.0
Requires-Dist: minify-html>=0.15.0
Requires-Dist: mistune>=3.1.1
Requires-Dist: pyyaml>=6.0.2
Requires-Dist: livereload>=2.7.1
Requires-Dist: GitPython>=3.1.44
Requires-Dist: jsonpath-ng>=1.7.0
Requires-Dist: feedgen>=1.0.0
Requires-Dist: pygments>=2.19.1
Requires-Dist: python-slugify>=8.0.4
